requests_ntlm2/__init__.py
requests_ntlm2/adapters.py
requests_ntlm2/connection.py
requests_ntlm2/core.py
requests_ntlm2/dance.py
requests_ntlm2/requests_ntlm2.py
requests_ntlm2-6.6.0.dist-info/LICENSE
requests_ntlm2-6.6.0.dist-info/METADATA
requests_ntlm2-6.6.0.dist-info/WHEEL
requests_ntlm2-6.6.0.dist-info/top_level.txt
requests_ntlm2-6.6.0.dist-info/RECORD
